VidBarcodeSimilarities/__init__.py
VidBarcodeSimilarities/model.py
VidBarcodeSimilarities/videobarcodesimilarities.py
VidBarcodeSimilarities-0.0.4.dist-info/METADATA
VidBarcodeSimilarities-0.0.4.dist-info/WHEEL
VidBarcodeSimilarities-0.0.4.dist-info/top_level.txt
VidBarcodeSimilarities-0.0.4.dist-info/RECORD
